morta/__init__.py
morta/_base_client.py
morta/_client.py
morta/_compat.py
morta/_constants.py
morta/_exceptions.py
morta/_files.py
morta/_models.py
morta/_qs.py
morta/_resource.py
morta/_response.py
morta/_streaming.py
morta/_types.py
morta/_version.py
morta/py.typed
morta/_utils/__init__.py
morta/_utils/_logs.py
morta/_utils/_proxy.py
morta/_utils/_reflection.py
morta/_utils/_resources_proxy.py
morta/_utils/_streams.py
morta/_utils/_sync.py
morta/_utils/_transform.py
morta/_utils/_typing.py
morta/_utils/_utils.py
morta/lib/.keep
morta/resources/__init__.py
morta/resources/integrations.py
morta/resources/notifications.py
morta/resources/permissions.py
morta/resources/comment_thread/__init__.py
morta/resources/comment_thread/comment.py
morta/resources/comment_thread/comment_thread.py
morta/resources/document/__init__.py
morta/resources/document/document.py
morta/resources/document/duplicate.py
morta/resources/document/section/__init__.py
morta/resources/document/section/response.py
morta/resources/document/section/section.py
morta/resources/hub/__init__.py
morta/resources/hub/ai_answer.py
morta/resources/hub/hub.py
morta/resources/hub/invite.py
morta/resources/hub/secrets.py
morta/resources/table/__init__.py
morta/resources/table/column.py
morta/resources/table/join.py
morta/resources/table/row.py
morta/resources/table/sync.py
morta/resources/table/table.py
morta/resources/table/views/__init__.py
morta/resources/table/views/columns.py
morta/resources/table/views/rows.py
morta/resources/table/views/views.py
morta/resources/user/__init__.py
morta/resources/user/apikey.py
morta/resources/user/hubs.py
morta/resources/user/tags.py
morta/resources/user/user.py
morta/types/__init__.py
morta/types/access_policy.py
morta/types/action.py
morta/types/answer.py
morta/types/base_request_context_param.py
morta/types/comment_thread_create_params.py
morta/types/comment_thread_create_response.py
morta/types/comment_thread_delete_response.py
morta-1.0.1.dist-info/METADATA
morta-1.0.1.dist-info/WHEEL
morta-1.0.1.dist-info/licenses/LICENSE
morta-1.0.1.dist-info/RECORD
